memecomplete/__init__.py
memecomplete/__main__.py
memecomplete/gui.py
memecomplete/tests/__init__.py
memecomplete/tests/conftest.py
memecomplete/tests/test_gui.py
memecomplete_desktop-0.2.dist-info/DESCRIPTION.rst
memecomplete_desktop-0.2.dist-info/METADATA
memecomplete_desktop-0.2.dist-info/RECORD
memecomplete_desktop-0.2.dist-info/WHEEL
memecomplete_desktop-0.2.dist-info/entry_points.txt
memecomplete_desktop-0.2.dist-info/metadata.json
memecomplete_desktop-0.2.dist-info/top_level.txt
tests/__init__.py
tests/conftest.py
tests/test_all.py
